ehdg_pupil_detector/__init__.py
ehdg_pupil_detector/ehdg_pupil_detector.py
ehdg_pupil_detector/haarcascade_eye.xml
ehdg_pupil_detector/haarcascade_eye_tree_eyeglasses.xml
ehdg_pupil_detector/opm_detector_config.json
ehdg_pupil_detector/opmtrack.py
ehdg_pupil_detector/opmtrack_plot.json
ehdg_pupil_detector/pnm_detector_config.json
ehdg_pupil_detector-4.0.4.dist-info/LICENSE
ehdg_pupil_detector-4.0.4.dist-info/METADATA
ehdg_pupil_detector-4.0.4.dist-info/WHEEL
ehdg_pupil_detector-4.0.4.dist-info/entry_points.txt
ehdg_pupil_detector-4.0.4.dist-info/top_level.txt
ehdg_pupil_detector-4.0.4.dist-info/RECORD
