Metadata-Version: 2.1
Name: ehdg_pupil_detector
Version: 4.0.4
Summary: Python Library for Pupil Detector of Eye Health Diagnostic Group
Author-email: Zaw Lin Tun <zawlintun1511@gmail.com>
Project-URL: Homepage, https://github.com/jtur044/ehdg_pupil_detector
Project-URL: Bug Tracker, https://github.com/jtur044/ehdg_pupil_detector/issues
Classifier: Programming Language :: Python :: 3
Classifier: License :: OSI Approved :: Apache Software License
Classifier: Operating System :: OS Independent
Requires-Python: >=3.9
License-File: LICENSE
Requires-Dist: setuptools >=61.0
Requires-Dist: opencv-python >=4.8.1.78
Requires-Dist: scipy >=1.11.3
Requires-Dist: numpy >=1.26.1
Requires-Dist: commentjson
Requires-Dist: ehdg-tools >=4.3.1
Requires-Dist: numpy
